[
  {
		"name": "Blobs",
		"author": "lazrdev",
		"url": "https://raw.githubusercontent.com/lazrdev/NothingMuch/master/wallpapers/Blobs.png",
		"dimensions": "2000x3000",
		"copyright": "Personal use only"
	},
  {
		"name": "Blocky",
		"author": "lazrdev",
		"url": "https://raw.githubusercontent.com/lazrdev/NothingMuch/master/wallpapers/Blocky.png",
		"dimensions": "2000x3000",
		"copyright": "Personal use only"
	},
  {
		"name": "Fans 2",
		"author": "lazrdev",
		"url": "https://raw.githubusercontent.com/lazrdev/NothingMuch/master/wallpapers/Fans%202.png",
		"dimensions": "2000x3000",
		"copyright": "Personal use only"
	},
  {
		"name": "Layers 2",
		"author": "lazrdev",
		"url": "https://raw.githubusercontent.com/lazrdev/NothingMuch/master/wallpapers/Layers%202.png",
		"dimensions": "2000x3000",
		"copyright": "Personal use only"
	},
  {
		"name": "Pipeland",
		"author": "lazrdev",
		"url": "https://raw.githubusercontent.com/lazrdev/NothingMuch/master/wallpapers/pipeland.png",
		"dimensions": "2000x3000",
		"copyright": "Personal use only"
	},
  {
		"name": "Prism",
		"author": "lazrdev",
		"url": "https://raw.githubusercontent.com/lazrdev/NothingMuch/master/wallpapers/Prism.png",
		"dimensions": "2000x3000",
		"copyright": "Personal use only"
	},
  {
		"name": "Fans",
		"author": "lazrdev",
		"url": "https://raw.githubusercontent.com/lazrdev/NothingMuch/master/wallpapers/Fans.png",
		"dimensions": "2000x3000",
		"copyright": "Personal use only"
	},
  {
		"name": "Layers",
		"author": "lazrdev",
		"url": "https://raw.githubusercontent.com/lazrdev/NothingMuch/master/wallpapers/Layers.png",
		"dimensions": "2000x3000",
		"copyright": "Personal use only"
	}
 ]
